jaraco/context/__init__.py
jaraco/context/py.typed
jaraco.context-6.0.1.dist-info/LICENSE
jaraco.context-6.0.1.dist-info/METADATA
jaraco.context-6.0.1.dist-info/WHEEL
jaraco.context-6.0.1.dist-info/top_level.txt
jaraco.context-6.0.1.dist-info/RECORD
